bestrag/__init__.py
bestrag/best_rag.py
bestrag-0.3.3.dist-info/LICENSE
bestrag-0.3.3.dist-info/METADATA
bestrag-0.3.3.dist-info/WHEEL
bestrag-0.3.3.dist-info/top_level.txt
bestrag-0.3.3.dist-info/RECORD
