Metadata-Version: 2.1
Name: bestrag
Version: 0.3.3
Summary: bestrag: Library for storing and searching document embeddings in a Qdrant vector database using hybrid embedding techniques.
Home-page: https://github.com/samadpls/bestRAG
Author: samadpls
Author-email: abdulsamadsid1@gmail.com
Classifier: Programming Language :: Python :: 3
Classifier: License :: OSI Approved :: MIT License
Classifier: Operating System :: OS Independent
Requires-Python: >=3.6
License-File: LICENSE
Requires-Dist: fastembed==0.4.1
Requires-Dist: PyPDF2==3.0.1
Requires-Dist: qdrant-client
Requires-Dist: onnxruntime==1.19.2
